{
  "date": "2015-12-29",
  "metals": {
    "copper": {
      "lme": {
        "cash": {
          "prev_close": 4692.5,
          "open": 4639.25,
          "high": 4750.25,
          "low": 4617.25,
          "close": 4730.75,
          "change": 38.25
        },
        "3m": {
          "prev_close": 4692.0,
          "open": 4639.0,
          "high": 4750.0,
          "low": 4617.0,
          "close": 4730.5,
          "change": 38.5
        },
        "bid": -3.75,
        "ask": 0.25,
        "open_interest": 285675
      },
      "settlement": {
        "cash": 4685.0,
        "3m": 4687.0,
        "monthly_avg": {
          "cash": 4808.24,
          "3m": 4794.71
        },
        "prev_monthly_avg": {
          "cash": 4727.25,
          "3m": 4729.0
        },
        "forwards": {
          "m1": 4735.25,
          "m2": 4735.5,
          "m3": 4731.75
        }
      },
      "inventory": {
        "prev": 235200,
        "in": 1875,
        "out": 0,
        "current": 237075,
        "change": 1875,
        "on_warrant": 200925,
        "cancelled_warrant": 36150,
        "cw_change": 4650
      },
      "shfe": {
        "lme_3m_cny": 30388,
        "lme_near_cny": 30421,
        "lme_3m_incl_tax": 35554,
        "lme_near_incl_tax": 35592,
        "shfe_3m": 35830,
        "shfe_settle": 36120,
        "premium_usd": 81.27
      }
    },
    "aluminum": {
      "lme": {
        "cash": {
          "prev_close": 1534.0,
          "open": 1519.25,
          "high": 1543.25,
          "low": 1490.75,
          "close": 1518.25,
          "change": -15.75
        },
        "3m": {
          "prev_close": 1535.0,
          "open": 1526.0,
          "high": 1550.0,
          "low": 1497.5,
          "close": 1525.0,
          "change": -10.0
        },
        "bid": -8.75,
        "ask": -6.75,
        "open_interest": 791074
      },
      "settlement": {
        "cash": 1535.0,
        "3m": 1541.0,
        "monthly_avg": {
          "cash": 1465.64,
          "3m": 1481.45
        },
        "prev_monthly_avg": {
          "cash": 1528.25,
          "3m": 1535.0
        },
        "forwards": {
          "m1": 1532.25,
          "m2": 1534.75,
          "m3": 1535.75
        }
      },
      "inventory": {
        "prev": 2914025,
        "in": 0,
        "out": 7100,
        "current": 2906925,
        "change": -7100,
        "on_warrant": 1816275,
        "cancelled_warrant": 1090650,
        "cw_change": -7100
      },
      "shfe": {
        "lme_3m_cny": 9862,
        "lme_near_cny": 9849,
        "lme_3m_incl_tax": 11539,
        "lme_near_incl_tax": 11524,
        "shfe_3m": 10625,
        "shfe_settle": 10800,
        "premium_usd": -111.62
      }
    },
    "zinc": {
      "lme": {
        "3m": {
          "prev_close": 1549.0,
          "open": 1545.0,
          "high": 1615.5,
          "low": 1526.0,
          "close": 1595.0,
          "change": 46.0
        },
        "bid": -16.75,
        "ask": -14.75,
        "open_interest": 288249
      },
      "settlement": {
        "cash": 1559.0,
        "3m": 1573.0,
        "monthly_avg": {
          "cash": 1582.29,
          "3m": 1603.9
        },
        "prev_monthly_avg": {
          "cash": 1586.25,
          "3m": 1602.0
        },
        "forwards": {
          "m1": 1594.75,
          "m2": 1598.75,
          "m3": 1603.0
        }
      },
      "inventory": {
        "prev": 470975,
        "in": 0,
        "out": 2500,
        "current": 468475,
        "change": -2500,
        "on_warrant": 406450,
        "cancelled_warrant": 62025,
        "cw_change": -2500
      },
      "shfe": {
        "lme_3m_cny": 10096,
        "lme_near_cny": 10049,
        "lme_3m_incl_tax": 11812,
        "lme_near_incl_tax": 11757,
        "shfe_3m": 12985,
        "shfe_settle": 13020,
        "premium_usd": 194.65
      }
    },
    "lead": {
      "lme": {
        "3m": {
          "prev_close": 1739.5,
          "open": 1737.0,
          "high": 1773.5,
          "low": 1716.0,
          "close": 1765.0,
          "change": 25.5
        },
        "bid": 7.5,
        "ask": 9.5,
        "open_interest": 131129
      },
      "settlement": {
        "cash": 1763.0,
        "3m": 1754.0,
        "monthly_avg": {
          "cash": 1615.98,
          "3m": 1625.62
        },
        "prev_monthly_avg": {
          "cash": 1776.5,
          "3m": 1768.0
        },
        "forwards": {
          "m1": 1772.5,
          "m2": 1773.0,
          "m3": 1771.0
        }
      },
      "inventory": {
        "prev": 191675,
        "in": 0,
        "out": 0,
        "current": 191675,
        "change": 0,
        "on_warrant": 80600,
        "cancelled_warrant": 111075,
        "cw_change": 25
      },
      "shfe": {
        "lme_3m_cny": 11244,
        "lme_near_cny": 11278,
        "lme_3m_incl_tax": 13155,
        "lme_near_incl_tax": 13195,
        "shfe_3m": 12905,
        "shfe_settle": 13040,
        "premium_usd": -23.98
      }
    },
    "nickel": {
      "lme": {
        "3m": {
          "prev_close": 8610.0,
          "open": 8560.0,
          "high": 8760.0,
          "low": 8440.0,
          "close": 8745.0,
          "change": 135.0
        },
        "bid": -48.0,
        "ask": -46.0,
        "open_interest": 245243
      },
      "settlement": {
        "cash": 8560.0,
        "3m": 8580.0,
        "monthly_avg": {
          "cash": 9232.14,
          "3m": 9274.05
        },
        "prev_monthly_avg": {
          "cash": 8707.0,
          "3m": 8750.0
        },
        "forwards": {
          "m1": 8717.0,
          "m2": 8730.5,
          "m3": 8744.0
        }
      },
      "inventory": {
        "prev": 445332,
        "in": 162,
        "out": 126,
        "current": 445368,
        "change": 36,
        "on_warrant": 275784,
        "cancelled_warrant": 169584,
        "cw_change": -126
      },
      "shfe": {
        "lme_3m_cny": 55718,
        "lme_near_cny": 55520,
        "lme_3m_incl_tax": 65190,
        "lme_near_incl_tax": 64958,
        "shfe_3m": 67820,
        "shfe_settle": 67260,
        "premium_usd": 354.77
      }
    },
    "tin": {
      "lme": {
        "3m": {
          "prev_close": 14565.0,
          "open": 14530.0,
          "high": 14750.0,
          "low": 14470.0,
          "close": 14735.0,
          "change": 170.0
        },
        "bid": 30.0,
        "ask": 32.0,
        "open_interest": 17425
      },
      "settlement": {
        "cash": 14595.0,
        "3m": 14505.0,
        "monthly_avg": {
          "cash": 14742.62,
          "3m": 14685.48
        },
        "prev_monthly_avg": {
          "cash": 14727.0,
          "3m": 14700.0
        },
        "forwards": {
          "m1": 14732.0,
          "m2": 14712.0,
          "m3": 14702.0
        }
      },
      "inventory": {
        "prev": 6675,
        "in": 0,
        "out": 180,
        "current": 6495,
        "change": -180,
        "on_warrant": 5715,
        "cancelled_warrant": 780,
        "cw_change": -180
      },
      "shfe": {
        "lme_3m_cny": 94344,
        "lme_near_cny": 94474,
        "lme_3m_incl_tax": 110383,
        "lme_near_incl_tax": 110535,
        "shfe_3m": 89310,
        "shfe_settle": 91810,
        "premium_usd": -2886.82
      }
    }
  },
  "ev_metals": {},
  "precious": {
    "gold": {
      "spot": 1068.73,
      "high": 1075.4,
      "low": 1067.95,
      "am_fix": 1067.25,
      "pm_fix": 1070.1
    },
    "silver": {
      "spot": 13.97,
      "high": 14.07,
      "low": 13.93,
      "am_fix": 13.93
    },
    "platinum": {
      "spot": 890.15,
      "high": 894.0,
      "low": 879.0,
      "am_fix": 883.0,
      "pm_fix": 895.0
    },
    "palladium": {
      "spot": 559.35,
      "high": 558.67,
      "low": 550.9,
      "am_fix": 552.0,
      "pm_fix": 558.0
    }
  },
  "fx": {
    "cny_usd": 6.4864
  },
  "market": {
    "sp500": null,
    "dow": 2079.91,
    "wti": null,
    "krw_usd": 37.87,
    "eur_usd": 1172.56,
    "jpy_usd": 1.0938,
    "sp500_change": null,
    "dow_change": 23.41,
    "wti_change": null,
    "krw_change": 1.06
  },
  "_warnings": [
    "ev: parse_ev_metals: list index out of range"
  ]
}