{
  "date": "2017-08-14",
  "metals": {
    "copper": {
      "lme": {
        "cash": {
          "prev_close": 6396.5,
          "open": 6402.5,
          "high": 6418.0,
          "low": 6349.0,
          "close": 6382.5,
          "change": -14.0
        },
        "3m": {
          "prev_close": 6422.5,
          "open": 6430.0,
          "high": 6445.5,
          "low": 6376.5,
          "close": 6410.0,
          "change": -12.5
        },
        "bid": -31.5,
        "ask": -27.5,
        "open_interest": 349644
      },
      "settlement": {
        "cash": 6351.0,
        "3m": 6383.0,
        "monthly_avg": {
          "cash": 5978.6,
          "3m": 6008.31
        },
        "prev_monthly_avg": {
          "cash": 6367.5,
          "3m": 6397.0
        },
        "forwards": {
          "m1": 6380.0,
          "m2": 6389.75,
          "m3": 6397.25
        }
      },
      "inventory": {
        "prev": 283675,
        "in": 5425,
        "out": 5775,
        "current": 283325,
        "change": -350,
        "on_warrant": 141300,
        "cancelled_warrant": 142025,
        "cw_change": 2450
      },
      "shfe": {
        "lme_3m_cny": 42693,
        "lme_near_cny": 42509,
        "lme_3m_incl_tax": 49951,
        "lme_near_incl_tax": 49736,
        "shfe_3m": 50440,
        "shfe_settle": 50280,
        "premium_usd": 81.54
      }
    },
    "aluminum": {
      "lme": {
        "cash": {
          "prev_close": 2041.25,
          "open": 2051.25,
          "high": 2053.75,
          "low": 2028.75,
          "close": 2032.25,
          "change": -9.0
        },
        "3m": {
          "prev_close": 2046.0,
          "open": 2045.0,
          "high": 2047.5,
          "low": 2022.5,
          "close": 2026.0,
          "change": -20.0
        },
        "bid": 2.25,
        "ask": 6.25,
        "open_interest": 674417
      },
      "settlement": {
        "cash": 2030.0,
        "3m": 2031.5,
        "monthly_avg": {
          "cash": 1903.62,
          "3m": 1921.36
        },
        "prev_monthly_avg": {
          "cash": 2027.25,
          "3m": 2023.0
        },
        "forwards": {
          "m1": 2012.25,
          "m2": 2018.75,
          "m3": 2023.25
        }
      },
      "inventory": {
        "prev": 1283825,
        "in": 15525,
        "out": 8100,
        "current": 1291250,
        "change": 7425,
        "on_warrant": 1040500,
        "cancelled_warrant": 250750,
        "cw_change": -1900
      },
      "shfe": {
        "lme_3m_cny": 13510,
        "lme_near_cny": 13482,
        "lme_3m_incl_tax": 15807,
        "lme_near_incl_tax": 15774,
        "shfe_3m": 16045,
        "shfe_settle": 15970,
        "premium_usd": 29.38
      }
    },
    "zinc": {
      "lme": {
        "3m": {
          "prev_close": 2897.0,
          "open": 2903.0,
          "high": 2924.5,
          "low": 2896.0,
          "close": 2917.0,
          "change": 20.0
        },
        "bid": -16.5,
        "ask": -14.5,
        "open_interest": 309278
      },
      "settlement": {
        "cash": 2891.0,
        "3m": 2910.5,
        "monthly_avg": {
          "cash": 2785.1,
          "3m": 2789.86
        },
        "prev_monthly_avg": {
          "cash": 2901.5,
          "3m": 2917.0
        },
        "forwards": {
          "m1": 2911.5,
          "m2": 2914.5,
          "m3": 2917.0
        }
      },
      "inventory": {
        "prev": 258300,
        "in": 0,
        "out": 3025,
        "current": 255275,
        "change": -3025,
        "on_warrant": 155300,
        "cancelled_warrant": 99975,
        "cw_change": -3025
      },
      "shfe": {
        "lme_3m_cny": 19395,
        "lme_near_cny": 19307,
        "lme_3m_incl_tax": 22692,
        "lme_near_incl_tax": 22589,
        "shfe_3m": 23935,
        "shfe_settle": 24065,
        "premium_usd": 221.29
      }
    },
    "lead": {
      "lme": {
        "3m": {
          "prev_close": 2332.0,
          "open": 2325.0,
          "high": 2349.0,
          "low": 2325.0,
          "close": 2340.0,
          "change": 8.0
        },
        "bid": -20.0,
        "ask": -18.0,
        "open_interest": 117465
      },
      "settlement": {
        "cash": 2317.0,
        "3m": 2337.0,
        "monthly_avg": {
          "cash": 2266.4,
          "3m": 2290.86
        },
        "prev_monthly_avg": {
          "cash": 2316.0,
          "3m": 2335.0
        },
        "forwards": {
          "m1": 2323.0,
          "m2": 2330.5,
          "m3": 2334.5
        }
      },
      "inventory": {
        "prev": 152050,
        "in": 0,
        "out": 125,
        "current": 151925,
        "change": -125,
        "on_warrant": 88000,
        "cancelled_warrant": 63925,
        "cw_change": -125
      },
      "shfe": {
        "lme_3m_cny": 15602,
        "lme_near_cny": 15467,
        "lme_3m_incl_tax": 18254,
        "lme_near_incl_tax": 18096,
        "shfe_3m": 19065,
        "shfe_settle": 19075,
        "premium_usd": 146.7
      }
    },
    "nickel": {
      "lme": {
        "3m": {
          "prev_close": 10655.0,
          "open": 10635.0,
          "high": 10725.0,
          "low": 10385.0,
          "close": 10430.0,
          "change": -225.0
        },
        "bid": -48.0,
        "ask": -38.0,
        "open_interest": 259688
      },
      "settlement": {
        "cash": 10510.0,
        "3m": 10590.0,
        "monthly_avg": {
          "cash": 9481.67,
          "3m": 9529.52
        },
        "prev_monthly_avg": {
          "cash": 10407.0,
          "3m": 10450.0
        },
        "forwards": {
          "m1": 10413.5,
          "m2": 10432.5,
          "m3": 10450.0
        }
      },
      "inventory": {
        "prev": 375696,
        "in": 0,
        "out": 408,
        "current": 375288,
        "change": -408,
        "on_warrant": 257430,
        "cancelled_warrant": 117858,
        "cw_change": -1836
      },
      "shfe": {
        "lme_3m_cny": 70588,
        "lme_near_cny": 70284,
        "lme_3m_incl_tax": 82588,
        "lme_near_incl_tax": 82232,
        "shfe_3m": 85830,
        "shfe_settle": 85930,
        "premium_usd": 554.22
      }
    },
    "tin": {
      "lme": {
        "3m": {
          "prev_close": 20300.0,
          "open": 20250.0,
          "high": 20400.0,
          "low": 20230.0,
          "close": 20320.0,
          "change": 20.0
        },
        "bid": 155.0,
        "ask": 165.0,
        "open_interest": 17795
      },
      "settlement": {
        "cash": 20525.0,
        "3m": 20330.0,
        "monthly_avg": {
          "cash": 20272.86,
          "3m": 20098.33
        },
        "prev_monthly_avg": {
          "cash": 20460.0,
          "3m": 20300.0
        },
        "forwards": {
          "m1": 20390.0,
          "m2": 20340.0,
          "m3": 20300.0
        }
      },
      "inventory": {
        "prev": 1730,
        "in": 0,
        "out": 0,
        "current": 1730,
        "change": 0,
        "on_warrant": 1595,
        "cancelled_warrant": 135,
        "cw_change": 0
      },
      "shfe": {
        "lme_3m_cny": 134971,
        "lme_near_cny": 135738,
        "lme_3m_incl_tax": 157916,
        "lme_near_incl_tax": 158813,
        "shfe_3m": 149450,
        "shfe_settle": 146610,
        "premium_usd": -1829.07
      }
    }
  },
  "ev_metals": {},
  "precious": {},
  "fx": {
    "cny_usd": 6.67
  },
  "market": {
    "sp500": null,
    "dow": 2465.47,
    "wti": null,
    "krw_usd": 49.08,
    "eur_usd": 1142.68,
    "jpy_usd": 1.1658,
    "sp500_change": null,
    "dow_change": 24.15,
    "wti_change": null,
    "krw_change": -0.31
  },
  "_warnings": [
    "ev: parse_ev_metals: list index out of range",
    "precious: parse_precious_metals: list index out of range"
  ]
}