{
  "date": "2018-01-12",
  "metals": {
    "copper": {
      "lme": {
        "cash": {
          "prev_close": 7099.75,
          "open": 7099.75,
          "high": 7137.25,
          "low": 7066.25,
          "close": 7073.75,
          "change": -26.0
        },
        "3m": {
          "prev_close": 7135.5,
          "open": 7133.5,
          "high": 7171.0,
          "low": 7100.0,
          "close": 7107.5,
          "change": -28.0
        },
        "bid": -37.75,
        "ask": -33.75,
        "open_interest": 339333
      },
      "settlement": {
        "cash": 7070.5,
        "3m": 7111.0,
        "monthly_avg": {
          "cash": 6801.16,
          "3m": 6839.03
        },
        "prev_monthly_avg": {
          "cash": 7074.25,
          "3m": 7110.0
        },
        "forwards": {
          "m1": 7074.75,
          "m2": 7087.75,
          "m3": 7100.75
        }
      },
      "inventory": {
        "prev": 201650,
        "in": 3350,
        "out": 875,
        "current": 204125,
        "change": 2475,
        "on_warrant": 157350,
        "cancelled_warrant": 46775,
        "cw_change": -875
      },
      "shfe": {
        "lme_3m_cny": 46374,
        "lme_near_cny": 45982,
        "lme_3m_incl_tax": 54258,
        "lme_near_incl_tax": 53799,
        "shfe_3m": 54830,
        "shfe_settle": 54510,
        "premium_usd": 109.78
      }
    },
    "aluminum": {
      "lme": {
        "cash": {
          "prev_close": 2175.25,
          "open": 2171.25,
          "high": 2220.75,
          "low": 2171.25,
          "close": 2212.25,
          "change": 37.0
        },
        "3m": {
          "prev_close": 2184.0,
          "open": 2180.5,
          "high": 2230.0,
          "low": 2180.5,
          "close": 2221.5,
          "change": 37.5
        },
        "bid": -13.25,
        "ask": -9.25,
        "open_interest": 723036
      },
      "settlement": {
        "cash": 2215.0,
        "3m": 2223.0,
        "monthly_avg": {
          "cash": 2070.74,
          "3m": 2087.34
        },
        "prev_monthly_avg": {
          "cash": 2202.75,
          "3m": 2214.0
        },
        "forwards": {
          "m1": 2203.25,
          "m2": 2210.25,
          "m3": 2210.75
        }
      },
      "inventory": {
        "prev": 1088325,
        "in": 1050,
        "out": 2500,
        "current": 1086875,
        "change": -1450,
        "on_warrant": 836375,
        "cancelled_warrant": 250500,
        "cw_change": 13500
      },
      "shfe": {
        "lme_3m_cny": 14231,
        "lme_near_cny": 14016,
        "lme_3m_incl_tax": 16651,
        "lme_near_incl_tax": 16399,
        "shfe_3m": 15200,
        "shfe_settle": 15020,
        "premium_usd": -213.01
      }
    },
    "zinc": {
      "lme": {
        "3m": {
          "prev_close": 3384.0,
          "open": 3380.0,
          "high": 3409.0,
          "low": 3373.0,
          "close": 3392.5,
          "change": 8.5
        },
        "bid": 51.0,
        "ask": 53.0,
        "open_interest": 316897
      },
      "settlement": {
        "cash": 3420.0,
        "3m": 3387.0,
        "monthly_avg": {
          "cash": 3192.47,
          "3m": 3188.71
        },
        "prev_monthly_avg": {
          "cash": 3435.5,
          "3m": 3383.5
        },
        "forwards": {
          "m1": 3433.5,
          "m2": 3398.5,
          "m3": 3388.5
        }
      },
      "inventory": {
        "prev": 180175,
        "in": 0,
        "out": 25,
        "current": 180150,
        "change": -25,
        "on_warrant": 126675,
        "cancelled_warrant": 53475,
        "cw_change": -25
      },
      "shfe": {
        "lme_3m_cny": 22022,
        "lme_near_cny": 22080,
        "lme_3m_incl_tax": 25766,
        "lme_near_incl_tax": 25834,
        "shfe_3m": 26250,
        "shfe_settle": 26240,
        "premium_usd": 62.77
      }
    },
    "lead": {
      "lme": {
        "3m": {
          "prev_close": 2552.5,
          "open": 2549.5,
          "high": 2563.5,
          "low": 2517.0,
          "close": 2537.5,
          "change": -15.0
        },
        "bid": 7.75,
        "ask": 9.75,
        "open_interest": 128533
      },
      "settlement": {
        "cash": 2536.0,
        "3m": 2530.0,
        "monthly_avg": {
          "cash": 2508.82,
          "3m": 2507.45
        },
        "prev_monthly_avg": {
          "cash": 2543.75,
          "3m": 2535.0
        },
        "forwards": {
          "m1": 2538.75,
          "m2": 2533.75,
          "m3": 2534.25
        }
      },
      "inventory": {
        "prev": 142575,
        "in": 0,
        "out": 500,
        "current": 142075,
        "change": -500,
        "on_warrant": 97275,
        "cancelled_warrant": 44800,
        "cw_change": -500
      },
      "shfe": {
        "lme_3m_cny": 16571,
        "lme_near_cny": 16502,
        "lme_3m_incl_tax": 19389,
        "lme_near_incl_tax": 19307,
        "shfe_3m": 19235,
        "shfe_settle": 19280,
        "premium_usd": -4.19
      }
    },
    "nickel": {
      "lme": {
        "3m": {
          "prev_close": 12610.0,
          "open": 12580.0,
          "high": 12745.0,
          "low": 12565.0,
          "close": 12655.0,
          "change": 45.0
        },
        "bid": -46.0,
        "ask": -36.0,
        "open_interest": 264167
      },
      "settlement": {
        "cash": 12670.0,
        "3m": 12690.0,
        "monthly_avg": {
          "cash": 11409.21,
          "3m": 11463.95
        },
        "prev_monthly_avg": {
          "cash": 12684.0,
          "3m": 12725.0
        },
        "forwards": {
          "m1": 12683.0,
          "m2": 12691.0,
          "m3": 12710.5
        }
      },
      "inventory": {
        "prev": 368292,
        "in": 0,
        "out": 2298,
        "current": 365994,
        "change": -2298,
        "on_warrant": 259272,
        "cancelled_warrant": 106722,
        "cw_change": -4968
      },
      "shfe": {
        "lme_3m_cny": 82080,
        "lme_near_cny": 81368,
        "lme_3m_incl_tax": 96034,
        "lme_near_incl_tax": 95201,
        "shfe_3m": 99040,
        "shfe_settle": 99090,
        "premium_usd": 600.83
      }
    },
    "tin": {
      "lme": {
        "3m": {
          "prev_close": 20180.0,
          "open": 20170.0,
          "high": 20275.0,
          "low": 20100.0,
          "close": 20265.0,
          "change": 85.0
        },
        "bid": 22.0,
        "ask": 32.0,
        "open_interest": 16753
      },
      "settlement": {
        "cash": 20275.0,
        "3m": 20275.0,
        "monthly_avg": {
          "cash": 19440.0,
          "3m": 19364.21
        },
        "prev_monthly_avg": {
          "cash": 20302.0,
          "3m": 20275.0
        },
        "forwards": {
          "m1": 20302.0,
          "m2": 20307.0,
          "m3": 20292.0
        }
      },
      "inventory": {
        "prev": 2235,
        "in": 30,
        "out": 150,
        "current": 2115,
        "change": -120,
        "on_warrant": 1450,
        "cancelled_warrant": 665,
        "cw_change": -110
      },
      "shfe": {
        "lme_3m_cny": 130564,
        "lme_near_cny": 131018,
        "lme_3m_incl_tax": 152760,
        "lme_near_incl_tax": 153291,
        "shfe_3m": 139500,
        "shfe_settle": 142820,
        "premium_usd": -1617.52
      }
    }
  },
  "ev_metals": {},
  "precious": {
    "gold": {
      "spot": 1332.04,
      "high": 1333.05,
      "low": 1321.83,
      "am_fix": 1332.9,
      "pm_fix": 1326.8
    },
    "silver": {
      "spot": 17.11,
      "high": 17.18,
      "low": 16.99,
      "am_fix": 17.12
    },
    "platinum": {
      "spot": 991.7,
      "high": 998.5,
      "low": 984.4,
      "am_fix": 995.0,
      "pm_fix": 991.0
    },
    "palladium": {
      "spot": 1114.7,
      "high": 1111.8,
      "low": 1088.1,
      "am_fix": 1086.0,
      "pm_fix": 1098.0
    }
  },
  "fx": {
    "cny_usd": 6.47
  },
  "market": {
    "sp500": null,
    "dow": 2781.51,
    "wti": null,
    "krw_usd": 63.89,
    "eur_usd": 1064.08,
    "jpy_usd": 1.2136,
    "sp500_change": null,
    "dow_change": 13.95,
    "wti_change": null,
    "krw_change": 0.09
  },
  "_warnings": [
    "ev: parse_ev_metals: list index out of range"
  ]
}