{
  "date": "2019-07-10",
  "metals": {
    "copper": {
      "lme": {
        "cash": {
          "prev_close": 5808.5,
          "open": 5819.5,
          "high": 5950.5,
          "low": 5809.0,
          "close": 5949.5,
          "change": 141.0
        },
        "3m": {
          "prev_close": 5820.0,
          "open": 5829.0,
          "high": 5960.0,
          "low": 5818.5,
          "close": 5959.0,
          "change": 139.0
        },
        "bid": -13.5,
        "ask": -9.5,
        "open_interest": 303994
      },
      "settlement": {
        "cash": 5862.5,
        "3m": 5880.0,
        "monthly_avg": {
          "cash": 5868.43,
          "3m": 5888.08
        },
        "prev_monthly_avg": {
          "cash": 5928.5,
          "3m": 5940.0
        },
        "forwards": {
          "m1": 5933.0,
          "m2": 5931.0,
          "m3": 5935.0
        }
      },
      "inventory": {
        "prev": 296025,
        "in": 100,
        "out": 2600,
        "current": 293525,
        "change": -2500,
        "on_warrant": 261325,
        "cancelled_warrant": 32200,
        "cw_change": -3100
      },
      "shfe": {
        "lme_3m_cny": 40231,
        "lme_near_cny": 40809,
        "lme_3m_incl_tax": 45461,
        "lme_near_incl_tax": 46114,
        "shfe_3m": 45940,
        "shfe_settle": 45870,
        "premium_usd": -35.49
      }
    },
    "aluminum": {
      "lme": {
        "cash": {
          "prev_close": 1808.5,
          "open": 1803.5,
          "high": 1837.5,
          "low": 1800.5,
          "close": 1836.0,
          "change": 27.5
        },
        "3m": {
          "prev_close": 1820.5,
          "open": 1818.5,
          "high": 1852.5,
          "low": 1815.5,
          "close": 1851.0,
          "change": 30.5
        },
        "bid": -17.0,
        "ask": -15.0,
        "open_interest": 695920
      },
      "settlement": {
        "cash": 1811.5,
        "3m": 1832.0,
        "monthly_avg": {
          "cash": 1754.08,
          "3m": 1782.05
        },
        "prev_monthly_avg": {
          "cash": 1833.0,
          "3m": 1850.0
        },
        "forwards": {
          "m1": 1835.5,
          "m2": 1844.5,
          "m3": 1848.5
        }
      },
      "inventory": {
        "prev": 948650,
        "in": 0,
        "out": 6900,
        "current": 941750,
        "change": -6900,
        "on_warrant": 634850,
        "cancelled_warrant": 306900,
        "cw_change": -6250
      },
      "shfe": {
        "lme_3m_cny": 12546,
        "lme_near_cny": 12625,
        "lme_3m_incl_tax": 14177,
        "lme_near_incl_tax": 14266,
        "shfe_3m": 13805,
        "shfe_settle": 13760,
        "premium_usd": -73.62
      }
    },
    "zinc": {
      "lme": {
        "3m": {
          "prev_close": 2364.0,
          "open": 2366.5,
          "high": 2409.5,
          "low": 2364.0,
          "close": 2405.0,
          "change": 41.0
        },
        "bid": 3.0,
        "ask": 5.0,
        "open_interest": 247301
      },
      "settlement": {
        "cash": 2381.0,
        "3m": 2381.0,
        "monthly_avg": {
          "cash": 2602.13,
          "3m": 2483.63
        },
        "prev_monthly_avg": {
          "cash": 2405.0,
          "3m": 2401.0
        },
        "forwards": {
          "m1": 2402.0,
          "m2": 2399.0,
          "m3": 2403.0
        }
      },
      "inventory": {
        "prev": 85550,
        "in": 0,
        "out": 2750,
        "current": 82800,
        "change": -2750,
        "on_warrant": 67875,
        "cancelled_warrant": 14925,
        "cw_change": -2725
      },
      "shfe": {
        "lme_3m_cny": 16453,
        "lme_near_cny": 16522,
        "lme_3m_incl_tax": 18592,
        "lme_near_incl_tax": 18669,
        "shfe_3m": 19040,
        "shfe_settle": 19100,
        "premium_usd": 62.59
      }
    },
    "lead": {
      "lme": {
        "3m": {
          "prev_close": 1932.0,
          "open": 1925.5,
          "high": 1964.5,
          "low": 1925.0,
          "close": 1962.0,
          "change": 30.0
        },
        "bid": 9.5,
        "ask": 11.5,
        "open_interest": 109562
      },
      "settlement": {
        "cash": 1955.0,
        "3m": 1943.5,
        "monthly_avg": {
          "cash": 1891.5,
          "3m": 1887.0
        },
        "prev_monthly_avg": {
          "cash": 1973.5,
          "3m": 1963.0
        },
        "forwards": {
          "m1": 1968.5,
          "m2": 1970.5,
          "m3": 1968.5
        }
      },
      "inventory": {
        "prev": 63650,
        "in": 0,
        "out": 100,
        "current": 63550,
        "change": -100,
        "on_warrant": 36650,
        "cancelled_warrant": 26900,
        "cw_change": -100
      },
      "shfe": {
        "lme_3m_cny": 13320,
        "lme_near_cny": 13540,
        "lme_3m_incl_tax": 15051,
        "lme_near_incl_tax": 15300,
        "shfe_3m": 15905,
        "shfe_settle": 15885,
        "premium_usd": 85.03
      }
    },
    "nickel": {
      "lme": {
        "3m": {
          "prev_close": 12725.0,
          "open": 12745.0,
          "high": 13030.0,
          "low": 12710.0,
          "close": 13010.0,
          "change": 285.0
        },
        "bid": -67.0,
        "ask": -57.0,
        "open_interest": 266977
      },
      "settlement": {
        "cash": 12790.0,
        "3m": 12850.0,
        "monthly_avg": {
          "cash": 11970.0,
          "3m": 12034.25
        },
        "prev_monthly_avg": {
          "cash": 12928.0,
          "3m": 12990.0
        },
        "forwards": {
          "m1": 12930.0,
          "m2": 12965.0,
          "m3": 12994.0
        }
      },
      "inventory": {
        "prev": 154104,
        "in": 0,
        "out": 492,
        "current": 153612,
        "change": -492,
        "on_warrant": 102864,
        "cancelled_warrant": 50748,
        "cw_change": -468
      },
      "shfe": {
        "lme_3m_cny": 88386,
        "lme_near_cny": 88936,
        "lme_3m_incl_tax": 99876,
        "lme_near_incl_tax": 100498,
        "shfe_3m": 101760,
        "shfe_settle": 101310,
        "premium_usd": 118.03
      }
    },
    "tin": {
      "lme": {
        "3m": {
          "prev_close": 18235.0,
          "open": 18230.0,
          "high": 18340.0,
          "low": 18025.0,
          "close": 18165.0,
          "change": -70.0
        },
        "bid": -52.0,
        "ask": -42.0,
        "open_interest": 16337
      },
      "settlement": {
        "cash": 18050.0,
        "3m": 18100.0,
        "monthly_avg": {
          "cash": 19176.5,
          "3m": 19075.75
        },
        "prev_monthly_avg": {
          "cash": 18148.0,
          "3m": 18195.0
        },
        "forwards": {
          "m1": 18155.0,
          "m2": 18180.0,
          "m3": 18200.0
        }
      },
      "inventory": {
        "prev": 6490,
        "in": 0,
        "out": 0,
        "current": 6490,
        "change": 0,
        "on_warrant": 5790,
        "cancelled_warrant": 700,
        "cw_change": 65
      },
      "shfe": {
        "lme_3m_cny": 125391,
        "lme_near_cny": 124876,
        "lme_3m_incl_tax": 141692,
        "lme_near_incl_tax": 141109,
        "shfe_3m": 134780,
        "shfe_settle": 138180,
        "premium_usd": -425.88
      }
    }
  },
  "ev_metals": {},
  "precious": {
    "gold": {
      "spot": 1411.92,
      "high": 1412.6,
      "low": 1390.2,
      "am_fix": 1395.45,
      "pm_fix": 1408.3
    },
    "silver": {
      "spot": 15.23,
      "high": 15.28,
      "low": 15.05,
      "am_fix": 15.1
    },
    "platinum": {
      "spot": 827.0,
      "high": 827.89,
      "low": 808.46,
      "am_fix": 813.0,
      "pm_fix": 823.0
    },
    "palladium": {
      "spot": 1595.5,
      "high": 1598.0,
      "low": 1546.22,
      "am_fix": 1550.0,
      "pm_fix": 1580.0
    }
  },
  "fx": {
    "cny_usd": 6.88
  },
  "market": {
    "sp500": 2993.95,
    "dow": 26871.11,
    "wti": 60.02,
    "krw_usd": 1176.26,
    "eur_usd": 1.1259,
    "jpy_usd": 108.48,
    "sp500_change": 14.32,
    "dow_change": 87.62,
    "wti_change": 2.19,
    "krw_change": -6.57
  },
  "_warnings": [
    "ev: parse_ev_metals: list index out of range"
  ]
}