{
  "date": "2021-01-26",
  "metals": {
    "copper": {
      "lme": {
        "cash": {
          "prev_close": 8002.5,
          "open": 7998.25,
          "high": 8030.25,
          "low": 7905.75,
          "close": 7986.75,
          "change": -15.75
        },
        "3m": {
          "prev_close": 8004.0,
          "open": 7997.5,
          "high": 8029.5,
          "low": 7905.0,
          "close": 7986.0,
          "change": -18.0
        },
        "bid": -3.25,
        "ask": 0.75,
        "open_interest": 312059
      },
      "settlement": {
        "cash": 7957.0,
        "3m": 7961.5,
        "monthly_avg": {
          "cash": 7755.24,
          "3m": 7771.5
        },
        "prev_monthly_avg": {
          "cash": 8007.25,
          "3m": 8008.5
        },
        "forwards": {
          "m1": 8011.75,
          "m2": 8011.75,
          "m3": 8010.75
        }
      },
      "inventory": {
        "prev": 82125,
        "in": 0,
        "out": 2850,
        "current": 79275,
        "change": -2850,
        "on_warrant": 53600,
        "cancelled_warrant": 25675,
        "cw_change": -1850
      },
      "shfe": {
        "lme_3m_cny": 51263,
        "lme_near_cny": 51282,
        "lme_3m_incl_tax": 57927,
        "lme_near_incl_tax": 57949,
        "shfe_3m": 58870,
        "shfe_settle": 58810,
        "premium_usd": 133.0
      }
    },
    "aluminum": {
      "lme": {
        "cash": {
          "prev_close": 2027.33,
          "open": 2026.25,
          "high": 2033.25,
          "low": 2010.75,
          "close": 2025.75,
          "change": -1.58
        },
        "3m": {
          "prev_close": 2017.0,
          "open": 2018.5,
          "high": 2025.5,
          "low": 2003.0,
          "close": 2018.0,
          "change": 1.0
        },
        "bid": 3.75,
        "ask": 7.75,
        "open_interest": 739270
      },
      "settlement": {
        "cash": 2025.0,
        "3m": 2018.0,
        "monthly_avg": {
          "cash": 2017.9,
          "3m": 2028.9
        },
        "prev_monthly_avg": {
          "cash": 2025.75,
          "3m": 2020.0
        },
        "forwards": {
          "m1": 2016.5,
          "m2": 2013.75,
          "m3": 2020.0
        }
      },
      "inventory": {
        "prev": 1412925,
        "in": 9625,
        "out": 2775,
        "current": 1419775,
        "change": 6850,
        "on_warrant": 1164825,
        "cancelled_warrant": 254950,
        "cw_change": 7725
      },
      "shfe": {
        "lme_3m_cny": 12970,
        "lme_near_cny": 12953,
        "lme_3m_incl_tax": 14656,
        "lme_near_incl_tax": 14637,
        "shfe_3m": 14880,
        "shfe_settle": 14880,
        "premium_usd": 37.56
      }
    },
    "zinc": {
      "lme": {
        "3m": {
          "prev_close": 2703.5,
          "open": 2704.0,
          "high": 2711.5,
          "low": 2640.5,
          "close": 2653.5,
          "change": -50.0
        },
        "bid": -24.75,
        "ask": -22.75,
        "open_interest": 231644
      },
      "settlement": {
        "cash": 2651.0,
        "3m": 2673.0,
        "monthly_avg": {
          "cash": 2782.36,
          "3m": 2809.14
        },
        "prev_monthly_avg": {
          "cash": 2632.75,
          "3m": 2656.5
        },
        "forwards": {
          "m1": 2639.5,
          "m2": 2648.75,
          "m3": 2655.75
        }
      },
      "inventory": {
        "prev": 189775,
        "in": 46300,
        "out": 1050,
        "current": 235025,
        "change": 45250,
        "on_warrant": 214750,
        "cancelled_warrant": 20275,
        "cw_change": -450
      },
      "shfe": {
        "lme_3m_cny": 17297,
        "lme_near_cny": 17195,
        "lme_3m_incl_tax": 19546,
        "lme_near_incl_tax": 19430,
        "shfe_3m": 20230,
        "shfe_settle": 20235,
        "premium_usd": 124.32
      }
    },
    "lead": {
      "lme": {
        "3m": {
          "prev_close": 2063.0,
          "open": 2048.0,
          "high": 2081.0,
          "low": 2040.0,
          "close": 2075.5,
          "change": 12.5
        },
        "bid": -17.75,
        "ask": -15.75,
        "open_interest": 111158
      },
      "settlement": {
        "cash": 2036.0,
        "3m": 2054.0,
        "monthly_avg": {
          "cash": 2018.6,
          "3m": 2028.62
        },
        "prev_monthly_avg": {
          "cash": 2061.25,
          "3m": 2078.0
        },
        "forwards": {
          "m1": 2070.5,
          "m2": 2078.5,
          "m3": 2079.0
        }
      },
      "inventory": {
        "prev": 113175,
        "in": 0,
        "out": 2675,
        "current": 110500,
        "change": -2675,
        "on_warrant": 67275,
        "cancelled_warrant": 43225,
        "cw_change": -2025
      },
      "shfe": {
        "lme_3m_cny": 13287,
        "lme_near_cny": 13228,
        "lme_3m_incl_tax": 15015,
        "lme_near_incl_tax": 14947,
        "shfe_3m": 15420,
        "shfe_settle": 15465,
        "premium_usd": 80.01
      }
    },
    "nickel": {
      "lme": {
        "3m": {
          "prev_close": 18290.0,
          "open": 18265.0,
          "high": 18350.0,
          "low": 18035.0,
          "close": 18100.0,
          "change": -190.0
        },
        "bid": -51.5,
        "ask": -41.5,
        "open_interest": 222385
      },
      "settlement": {
        "cash": 18142.0,
        "3m": 18197.0,
        "monthly_avg": {
          "cash": 16807.05,
          "3m": 16870.0
        },
        "prev_monthly_avg": {
          "cash": 18010.5,
          "3m": 18057.0
        },
        "forwards": {
          "m1": 18023.5,
          "m2": 18039.5,
          "m3": 18055.5
        }
      },
      "inventory": {
        "prev": 248844,
        "in": 72,
        "out": 228,
        "current": 248688,
        "change": -156,
        "on_warrant": 185388,
        "cancelled_warrant": 63300,
        "cw_change": -228
      },
      "shfe": {
        "lme_3m_cny": 117212,
        "lme_near_cny": 116987,
        "lme_3m_incl_tax": 132449,
        "lme_near_incl_tax": 132195,
        "shfe_3m": 135320,
        "shfe_settle": 135460,
        "premium_usd": 504.48
      }
    },
    "tin": {
      "lme": {
        "3m": {
          "prev_close": 22430.0,
          "open": 22490.0,
          "high": 22900.0,
          "low": 22400.0,
          "close": 22840.0,
          "change": 410.0
        },
        "bid": 440.0,
        "ask": 450.0,
        "open_interest": 16374
      },
      "settlement": {
        "cash": 23280.0,
        "3m": 22790.0,
        "monthly_avg": {
          "cash": 19727.33,
          "3m": 19642.52
        },
        "prev_monthly_avg": {
          "cash": 23295.0,
          "3m": 22850.0
        },
        "forwards": {
          "m1": 23245.0,
          "m2": 23060.0,
          "m3": 22910.0
        }
      },
      "inventory": {
        "prev": 1045,
        "in": 25,
        "out": 40,
        "current": 1030,
        "change": -15,
        "on_warrant": 645,
        "cancelled_warrant": 385,
        "cw_change": -10
      },
      "shfe": {
        "lme_3m_cny": 145625,
        "lme_near_cny": 147987,
        "lme_3m_incl_tax": 164556,
        "lme_near_incl_tax": 167225,
        "shfe_3m": 170610,
        "shfe_settle": 170800,
        "premium_usd": 552.34
      }
    }
  },
  "ev_metals": {},
  "precious": {},
  "fx": {
    "cny_usd": 6.4722
  },
  "market": {
    "sp500": 3850.78,
    "dow": 30955.51,
    "wti": 52.56,
    "krw_usd": 1103.86,
    "eur_usd": 1.2159,
    "jpy_usd": 103.69,
    "sp500_change": -4.58,
    "dow_change": -4.49,
    "wti_change": -0.21,
    "krw_change": 0.43
  },
  "_warnings": [
    "ev: parse_ev_metals: list index out of range",
    "precious: parse_precious_metals: list index out of range"
  ]
}