{
  "date": "2021-04-01",
  "metals": {
    "copper": {
      "lme": {
        "cash": {
          "prev_close": 8808.25,
          "open": 8788.5,
          "high": 8829.5,
          "low": 8701.5,
          "close": 8796.5,
          "change": -11.75
        },
        "3m": {
          "prev_close": 8804.0,
          "open": 8782.0,
          "high": 8823.0,
          "low": 8695.0,
          "close": 8790.0,
          "change": -14.0
        },
        "bid": 2.5,
        "ask": 6.5,
        "open_interest": 303533
      },
      "settlement": {
        "cash": 8768.0,
        "3m": 8764.0,
        "monthly_avg": {
          "cash": 9004.98,
          "3m": 8988.2
        },
        "prev_monthly_avg": {
          "cash": 8794.5,
          "3m": 8790.0
        },
        "forwards": {
          "m1": 8799.5,
          "m2": 8795.0,
          "m3": 8792.75
        }
      },
      "inventory": {
        "prev": 144500,
        "in": 50,
        "out": 775,
        "current": 143775,
        "change": -725,
        "on_warrant": 108375,
        "cancelled_warrant": 35400,
        "cw_change": -2275
      },
      "shfe": {
        "lme_3m_cny": 57256,
        "lme_near_cny": 57305,
        "lme_3m_incl_tax": 64699,
        "lme_near_incl_tax": 64755,
        "shfe_3m": 65710,
        "shfe_settle": 65530,
        "premium_usd": 117.83
      }
    },
    "aluminum": {
      "lme": {
        "cash": {
          "prev_close": 2193.5,
          "open": 2194.5,
          "high": 2218.5,
          "low": 2192.5,
          "close": 2207.0,
          "change": 13.5
        },
        "3m": {
          "prev_close": 2216.0,
          "open": 2215.0,
          "high": 2239.0,
          "low": 2213.0,
          "close": 2227.5,
          "change": 11.5
        },
        "bid": -24.5,
        "ask": -20.5,
        "open_interest": 712001
      },
      "settlement": {
        "cash": 2212.5,
        "3m": 2236.5,
        "monthly_avg": {
          "cash": 2191.59,
          "3m": 2212.17
        },
        "prev_monthly_avg": {
          "cash": 2203.0,
          "3m": 2225.5
        },
        "forwards": {
          "m1": 2209.25,
          "m2": 2214.75,
          "m3": 2221.75
        }
      },
      "inventory": {
        "prev": 1897075,
        "in": 0,
        "out": 7675,
        "current": 1889400,
        "change": -7675,
        "on_warrant": 1333350,
        "cancelled_warrant": 556050,
        "cw_change": -10675
      },
      "shfe": {
        "lme_3m_cny": 14607,
        "lme_near_cny": 14491,
        "lme_3m_incl_tax": 16506,
        "lme_near_incl_tax": 16375,
        "shfe_3m": 17240,
        "shfe_settle": 17280,
        "premium_usd": 137.7
      }
    },
    "zinc": {
      "lme": {
        "3m": {
          "prev_close": 2806.5,
          "open": 2802.5,
          "high": 2816.0,
          "low": 2765.0,
          "close": 2768.5,
          "change": -38.0
        },
        "bid": -18.35,
        "ask": -16.35,
        "open_interest": 232404
      },
      "settlement": {
        "cash": 2765.5,
        "3m": 2781.5,
        "monthly_avg": {
          "cash": 2791.65,
          "3m": 2808.54
        },
        "prev_monthly_avg": {
          "cash": 2757.15,
          "3m": 2774.5
        },
        "forwards": {
          "m1": 2760.9,
          "m2": 2766.85,
          "m3": 2772.1
        }
      },
      "inventory": {
        "prev": 270850,
        "in": 0,
        "out": 350,
        "current": 270500,
        "change": -350,
        "on_warrant": 236425,
        "cancelled_warrant": 34075,
        "cw_change": 650
      },
      "shfe": {
        "lme_3m_cny": 18352,
        "lme_near_cny": 18278,
        "lme_3m_incl_tax": 20738,
        "lme_near_incl_tax": 20654,
        "shfe_3m": 21535,
        "shfe_settle": 21585,
        "premium_usd": 141.52
      }
    },
    "lead": {
      "lme": {
        "3m": {
          "prev_close": 1975.0,
          "open": 1979.5,
          "high": 1986.5,
          "low": 1954.0,
          "close": 1961.0,
          "change": -14.0
        },
        "bid": -22.95,
        "ask": -20.95,
        "open_interest": 101943
      },
      "settlement": {
        "cash": 1942.5,
        "3m": 1967.5,
        "monthly_avg": {
          "cash": 1960.76,
          "3m": 1982.72
        },
        "prev_monthly_avg": {
          "cash": 1941.55,
          "3m": 1963.5
        },
        "forwards": {
          "m1": 1945.75,
          "m2": 1954.75,
          "m3": 1960.75
        }
      },
      "inventory": {
        "prev": 119675,
        "in": 0,
        "out": 125,
        "current": 119550,
        "change": -125,
        "on_warrant": 101900,
        "cancelled_warrant": 17650,
        "cw_change": -125
      },
      "shfe": {
        "lme_3m_cny": 12914,
        "lme_near_cny": 12799,
        "lme_3m_incl_tax": 14593,
        "lme_near_incl_tax": 14463,
        "shfe_3m": 15325,
        "shfe_settle": 15300,
        "premium_usd": 127.27
      }
    },
    "nickel": {
      "lme": {
        "3m": {
          "prev_close": 16100.0,
          "open": 16175.0,
          "high": 16250.0,
          "low": 15940.0,
          "close": 16215.0,
          "change": 115.0
        },
        "bid": -51.5,
        "ask": -41.5,
        "open_interest": 215537
      },
      "settlement": {
        "cash": 16001.0,
        "3m": 16048.0,
        "monthly_avg": {
          "cash": 16460.74,
          "3m": 16506.3
        },
        "prev_monthly_avg": {
          "cash": 16167.5,
          "3m": 16214.0
        },
        "forwards": {
          "m1": 16172.5,
          "m2": 16189.0,
          "m3": 16204.0
        }
      },
      "inventory": {
        "prev": 260244,
        "in": 0,
        "out": 1062,
        "current": 259182,
        "change": -1062,
        "on_warrant": 197490,
        "cancelled_warrant": 61692,
        "cw_change": -834
      },
      "shfe": {
        "lme_3m_cny": 105537,
        "lme_near_cny": 105287,
        "lme_3m_incl_tax": 119257,
        "lme_near_incl_tax": 118974,
        "shfe_3m": 121160,
        "shfe_settle": 120990,
        "premium_usd": 306.56
      }
    },
    "tin": {
      "lme": {
        "3m": {
          "prev_close": 25225.0,
          "open": 25220.0,
          "high": 25450.0,
          "low": 24685.0,
          "close": 25120.0,
          "change": -105.0
        },
        "bid": 1550.0,
        "ask": 1560.0,
        "open_interest": 12291
      },
      "settlement": {
        "cash": 27369.0,
        "3m": 25202.0,
        "monthly_avg": {
          "cash": 27396.3,
          "3m": 25078.65
        },
        "prev_monthly_avg": {
          "cash": 26678.0,
          "3m": 25123.0
        },
        "forwards": {
          "m1": 26673.0,
          "m2": 26123.0,
          "m3": 25623.0
        }
      },
      "inventory": {
        "prev": 1770,
        "in": 0,
        "out": 30,
        "current": 1740,
        "change": -30,
        "on_warrant": 1505,
        "cancelled_warrant": 235,
        "cw_change": -20
      },
      "shfe": {
        "lme_3m_cny": 165571,
        "lme_near_cny": 179708,
        "lme_3m_incl_tax": 187095,
        "lme_near_incl_tax": 203071,
        "shfe_3m": 176440,
        "shfe_settle": 175670,
        "premium_usd": -4167.06
      }
    }
  },
  "ev_metals": {},
  "precious": {},
  "fx": {
    "cny_usd": 6.5755
  },
  "market": {
    "sp500": 4012.03,
    "dow": 33135.84,
    "wti": 60.47,
    "krw_usd": 1128.91,
    "eur_usd": 1.1775,
    "jpy_usd": 110.59,
    "sp500_change": 39.14,
    "dow_change": 154.29,
    "wti_change": 1.31,
    "krw_change": -0.15
  },
  "_warnings": [
    "ev: parse_ev_metals: list index out of range",
    "precious: parse_precious_metals: list index out of range"
  ]
}