{
  "date": "2025-05-13",
  "metals": {
    "copper": {
      "lme": {
        "cash": {
          "prev_close": 9534.87,
          "open": 9536.17,
          "high": 9643.67,
          "low": 9510.67,
          "close": 9637.67,
          "change": 102.8
        },
        "3m": {
          "prev_close": 9509.0,
          "open": 9515.0,
          "high": 9622.5,
          "low": 9489.5,
          "close": 9616.5,
          "change": 107.5
        },
        "bid": 17.17,
        "ask": 21.17,
        "open_interest": 289770
      },
      "settlement": {
        "cash": 9534.0,
        "3m": 9548.0,
        "monthly_avg": {
          "cash": 9192.13,
          "3m": 9219.4
        },
        "prev_monthly_avg": {
          "cash": 9618.67,
          "3m": 9599.5
        },
        "forwards": {
          "m1": 9624.54,
          "m2": 9627.4,
          "m3": 9614.54
        }
      },
      "inventory": {
        "prev": 190750,
        "in": 0,
        "out": 1100,
        "current": 189650,
        "change": -1100,
        "on_warrant": 108375,
        "cancelled_warrant": 81275,
        "cw_change": -925
      },
      "shfe": {
        "lme_3m_cny": 68856,
        "lme_near_cny": 69036,
        "lme_3m_incl_tax": 77807,
        "lme_near_incl_tax": 78010,
        "shfe_3m": 77080,
        "shfe_settle": 77880,
        "premium_usd": -18.12
      }
    },
    "aluminum": {
      "lme": {
        "cash": {
          "prev_close": 2468.16,
          "open": 2476.32,
          "high": 2496.32,
          "low": 2472.32,
          "close": 2495.32,
          "change": 27.16
        },
        "3m": {
          "prev_close": 2471.5,
          "open": 2471.5,
          "high": 2491.5,
          "low": 2467.5,
          "close": 2490.5,
          "change": 19.0
        },
        "bid": 0.82,
        "ask": 4.82,
        "open_interest": 719272
      },
      "settlement": {
        "cash": 2470.0,
        "3m": 2472.0,
        "monthly_avg": {
          "cash": 2381.25,
          "3m": 2415.83
        },
        "prev_monthly_avg": {
          "cash": 2492.82,
          "3m": 2490.0
        },
        "forwards": {
          "m1": 2494.78,
          "m2": 2491.08,
          "m3": 2491.17
        }
      },
      "inventory": {
        "prev": 401525,
        "in": 0,
        "out": 2225,
        "current": 399300,
        "change": -2225,
        "on_warrant": 249875,
        "cancelled_warrant": 149425,
        "cw_change": -1925
      },
      "shfe": {
        "lme_3m_cny": 17810,
        "lme_near_cny": 17844,
        "lme_3m_incl_tax": 20125,
        "lme_near_incl_tax": 20164,
        "shfe_3m": 19895,
        "shfe_settle": 19995,
        "premium_usd": -23.45
      }
    },
    "zinc": {
      "lme": {
        "3m": {
          "prev_close": 2675.0,
          "open": 2691.5,
          "high": 2721.0,
          "low": 2653.0,
          "close": 2720.0,
          "change": 45.0
        },
        "bid": -28.34,
        "ask": -26.34,
        "open_interest": 220039
      },
      "settlement": {
        "cash": 2638.5,
        "3m": 2670.5,
        "monthly_avg": {
          "cash": 2625.33,
          "3m": 2651.63
        },
        "prev_monthly_avg": {
          "cash": 2677.66,
          "3m": 2705.0
        },
        "forwards": {
          "m1": 2681.28,
          "m2": 2690.54,
          "m3": 2697.81
        }
      },
      "inventory": {
        "prev": 169850,
        "in": 200,
        "out": 2100,
        "current": 167950,
        "change": -1900,
        "on_warrant": 93750,
        "cancelled_warrant": 74200,
        "cw_change": -1900
      },
      "shfe": {
        "lme_3m_cny": 19289,
        "lme_near_cny": 19119,
        "lme_3m_incl_tax": 21797,
        "lme_near_incl_tax": 21604,
        "shfe_3m": 22105,
        "shfe_settle": 22330,
        "premium_usd": 100.84
      }
    },
    "lead": {
      "lme": {
        "3m": {
          "prev_close": 1974.0,
          "open": 1973.5,
          "high": 1997.0,
          "low": 1970.0,
          "close": 1989.5,
          "change": 15.5
        },
        "bid": -4.71,
        "ask": -2.71,
        "open_interest": 148000
      },
      "settlement": {
        "cash": 1987.0,
        "3m": 1991.5,
        "monthly_avg": {
          "cash": 1909.13,
          "3m": 1932.08
        },
        "prev_monthly_avg": {
          "cash": 1985.29,
          "3m": 1989.0
        },
        "forwards": {
          "m1": 1986.79,
          "m2": 1987.36,
          "m3": 1987.61
        }
      },
      "inventory": {
        "prev": 251800,
        "in": 1375,
        "out": 0,
        "current": 253175,
        "change": 1375,
        "on_warrant": 121650,
        "cancelled_warrant": 131525,
        "cw_change": 150
      },
      "shfe": {
        "lme_3m_cny": 14350,
        "lme_near_cny": 14334,
        "lme_3m_incl_tax": 16215,
        "lme_near_incl_tax": 16198,
        "shfe_3m": 16950,
        "shfe_settle": 16950,
        "premium_usd": 104.51
      }
    },
    "nickel": {
      "lme": {
        "3m": {
          "prev_close": 15560.0,
          "open": 15565.0,
          "high": 15755.0,
          "low": 15470.0,
          "close": 15730.0,
          "change": 170.0
        },
        "bid": -198.68,
        "ask": -188.68,
        "open_interest": 244973
      },
      "settlement": {
        "cash": 15475.0,
        "3m": 15650.0,
        "monthly_avg": {
          "cash": 15209.5,
          "3m": 15414.75
        },
        "prev_monthly_avg": {
          "cash": 15541.32,
          "3m": 15735.0
        },
        "forwards": {
          "m1": 15558.82,
          "m2": 15618.63,
          "m3": 15680.0
        }
      },
      "inventory": {
        "prev": 197754,
        "in": 762,
        "out": 0,
        "current": 198516,
        "change": 762,
        "on_warrant": 181308,
        "cancelled_warrant": 17208,
        "cw_change": 1566
      },
      "shfe": {
        "lme_3m_cny": 112035,
        "lme_near_cny": 110767,
        "lme_3m_incl_tax": 126600,
        "lme_near_incl_tax": 125166,
        "shfe_3m": 124530,
        "shfe_settle": 124230,
        "premium_usd": -130.03
      }
    },
    "tin": {
      "lme": {
        "3m": {
          "prev_close": 32425.0,
          "open": 32420.0,
          "high": 32880.0,
          "low": 32170.0,
          "close": 32725.0,
          "change": 300.0
        },
        "bid": -23.5,
        "ask": -13.5,
        "open_interest": 23487
      },
      "settlement": {
        "cash": 32620.0,
        "3m": 32750.0,
        "monthly_avg": {
          "cash": 32691.25,
          "3m": 32731.0
        },
        "prev_monthly_avg": {
          "cash": 32702.5,
          "3m": 32721.0
        },
        "forwards": {
          "m1": 32686.0,
          "m2": 32671.0,
          "m3": 32721.0
        }
      },
      "inventory": {
        "prev": 2790,
        "in": 0,
        "out": 0,
        "current": 2790,
        "change": 0,
        "on_warrant": 2345,
        "cancelled_warrant": 445,
        "cw_change": 135
      },
      "shfe": {
        "lme_3m_cny": 233934,
        "lme_near_cny": 233682,
        "lme_3m_incl_tax": 264346,
        "lme_near_incl_tax": 264061,
        "shfe_3m": 262910,
        "shfe_settle": 263340,
        "premium_usd": -100.17
      }
    }
  },
  "ev_metals": {
    "cobalt": {
      "may25": 34965.27,
      "jul25": 36111.68
    },
    "lithium": {
      "may25": 19003.82
    }
  },
  "precious": {
    "gold": {
      "spot": 3251.85,
      "high": 3265.18,
      "low": 3216.49
    },
    "silver": {
      "spot": 32.992,
      "high": 33.232,
      "low": 32.526
    },
    "platinum": {
      "spot": 997.13,
      "high": 992.8,
      "low": 983.65,
      "am_fix": 990.0,
      "pm_fix": 990.0
    },
    "palladium": {
      "spot": 962.31,
      "high": 960.19,
      "low": 940.57,
      "am_fix": 950.0,
      "pm_fix": 950.0
    }
  },
  "fx": {
    "cny_usd": 7.2002
  },
  "market": {
    "sp500": 5897.64,
    "dow": 42214.47,
    "wti": 63.81,
    "krw_usd": 1417.64,
    "eur_usd": 1.1177,
    "jpy_usd": 147.64,
    "sp500_change": 53.45,
    "dow_change": -195.63,
    "wti_change": 1.86,
    "krw_change": -2.91
  }
}